<?xml version="1.0" encoding="utf-8"?>
<ModsConfigData>
    <version>1.4.3704 rev896</version>
    <activeMods>
        <li>brrainz.harmony</li>
        <li>ludeon.rimworld</li>
        <li>bs.performance</li>
        <li>automatic.startupimpact</li>
        <li>ludeon.rimworld.royalty</li>
        <li>ludeon.rimworld.ideology</li>
        <li>ludeon.rimworld.biotech</li>
        <li>vanillaexpanded.backgrounds</li>
        <li>unlimitedhugs.hugslib</li>
        <li>brrainz.achtung</li>
        <li>pal5k.agrihandcleansweeperretexture</li>
        <li>nep.smallerturbines</li>
        <li>mehni.allyourbase</li>
        <li>unlimitedhugs.allowtool</li>
        <li>roolo.almostthere</li>
        <li>vanillaexpanded.achievements</li>
        <li>sumghai.replimat</li>
        <li>oskarpotocki.vanillafactionsexpanded.core</li>
        <li>vanillaexpanded.vcef</li>
        <li>sarg.rimbees</li>
        <li>jelly.rbstuffed</li>
        <li>vanillaexpanded.vpsycastse</li>
        <li>sarg.alphaanimals</li>
        <li>sarg.alphagenes</li>
        <li>vanillaexpanded.vbookse</li>
        <li>vanillaexpanded.vcooke</li>
        <li>vanillaexpanded.vmemese</li>
        <li>sarg.alphamemes</li>
        <li>vanillaexpanded.vfea</li>
        <li>oskarpotocki.vfe.empire</li>
        <li>vanillaexpanded.vwe</li>
        <li>vanillaexpanded.vwel</li>
        <li>oskarpotocki.vfe.pirates</li>
        <li>oskarpotocki.vfe.vikings</li>
        <li>hlx.ultratechalteredcarbon</li>
        <li>v1024.ebframework</li>
        <li>explodoboy.snsambitioncosmic</li>
        <li>explodoboy.snsambitioncosmic.gen4addon</li>
        <li>aw.mech.helmets</li>
        <li>shut.the.har.up</li>
        <li>erdelf.humanoidalienraces</li>
        <li>killathon.androidtiersreforged</li>
        <li>mlie.androidtierstxseries</li>
        <li>hh.xrushha.animaanimalscombined</li>
        <li>jp.animalslikehay</li>
        <li>oblitus.animalslogic</li>
        <li>revolus.animalsarefun</li>
        <li>oskarpotocki.vanillafactionsexpanded.settlersmodule</li>
        <li>atk.anthrosonae</li>
        <li>allezsoyez.anyplant.anyplant</li>
        <li>teok25.archotechexpanded.prosthetics</li>
        <li>jangodsoul.archotech.powerarmor</li>
        <li>razor2.3.anotherrimworldmod.autocutblight</li>
        <li>nibato.autoextractgenes</li>
        <li>ben.automaticnudistoutfit</li>
        <li>ben.automaticslaveoutfit</li>
        <li>bk.babypaste</li>
        <li>telardo.bettergenegraphicsframework</li>
        <li>drummeur.betterlinkablecolors</li>
        <li>steve.betterquestrewards</li>
        <li>largemoron.betterscenarioresearch</li>
        <li>biotexpans.core</li>
        <li>biotexpans.mammalia</li>
        <li>biotexpans.earpatch</li>
        <li>biotexpans.mythic</li>
        <li>mrchimick.blockunwantedminutiae</li>
        <li>sx99.biotech.bloodcolorgenes</li>
        <li>fluffy.blueprints</li>
        <li>vanillaexpanded.vanillaanimalsexpanded</li>
        <li>oskarpotocki.vfe.insectoid</li>
        <li>vanillaexpanded.vfepower</li>
        <li>vanillaexpanded.vchemfuele</li>
        <li>vanillaexpanded.vgeneticse</li>
        <li>mysticfelines.boomanimalsbleedchemfuel</li>
        <li>spankyh.bunrace.core</li>
        <li>brrainz.cameraplus</li>
        <li>monkey5206.carrycapacityfixed</li>
        <li>nephlite.carryalls</li>
        <li>void.charactereditor</li>
        <li>neronix17.retexture.charactereditor</li>
        <li>avilmask.commonsense</li>
        <li>miyamiya.compressedraid.latest</li>
        <li>sea.consistentgeneinheritance</li>
        <li>mlie.convertthenrecruit</li>
        <li>teiwaz.coverall</li>
        <li>tammybee.cutplantsbeforebuilding</li>
        <li>chris.cutercatearreplacer</li>
        <li>trojan.deathrattle</li>
        <li>drgsp.halituisamaricanus</li>
        <li>merthsoft.designatorshapes</li>
        <li>kb.prioritizeresearch</li>
        <li>dubwise.dubsmintmenus</li>
        <li>dubwise.dubsperformanceanalyzer.steam</li>
        <li>dubwise.rimatomics</li>
        <li>mlie.ducksnolimitsideology</li>
        <li>cocaine.electricstonecuttingtable</li>
        <li>erin.koyan</li>
        <li>wit.expandedroofing</li>
        <li>malistaticy.mer</li>
        <li>witek.fabricorscanrepairmechs</li>
        <li>kosaro.fahrenheitandcelsius</li>
        <li>garethp.familytree</li>
        <li>inglix.fasterbiosculptingpod</li>
        <li>vanillastorytellersexpanded.winstonwave</li>
        <li>imranfish.xmlextensions</li>
        <li>fastergene.recovery</li>
        <li>kathanon.floatsubmenu</li>
        <li>stevezero.fullarmorhandsfeet</li>
        <li>danielwedemeyer.generipper</li>
        <li>tac.genetrader</li>
        <li>telefonmast.graphicssettings</li>
        <li>fridgebaron.immortals</li>
        <li>rince.immortalsgene</li>
        <li>400.impassablehchestudeephwater</li>
        <li>knight.infiniteturrets</li>
        <li>haecriver.injuredcarry</li>
        <li>turnovus.biotech.integratedgenes</li>
        <li>nestofmoon.jobslimittweak</li>
        <li>brrainz.justignoremepassing</li>
        <li>ubergarm.kanbanstockpile</li>
        <li>ducks.insaneskills</li>
        <li>jaxe.rimhud</li>
        <li>vanillaexpanded.skills</li>
        <li>alias.degeneralizework</li>
        <li>seioch.kurin.har</li>
        <li>leion247109.laserhguns</li>
        <li>xavior.lifesupport</li>
        <li>murmur.walllight</li>
        <li>juanlopez2008.lightsout</li>
        <li>doctorstupid.sofa</li>
        <li>owlchemist.midsaversaver</li>
        <li>gene.miracle</li>
        <li>arquebus.moregenecomplexity</li>
        <li>arquebus.morepersonatraits</li>
        <li>llunak.moreprecepts</li>
        <li>seioch.naki.har</li>
        <li>jdalt.nomorelethaldamagethreshold</li>
        <li>xenofell.offspringinheritxenogenes</li>
        <li>ogre.ogrestack</li>
        <li>redundant.oopsallgenepacks</li>
        <li>sarg.magicalmenagerie</li>
        <li>vanillaexpanded.vaecaves</li>
        <li>vanillaexpanded.vaeendandext</li>
        <li>vanillaexpanded.vaeroy</li>
        <li>scorpio.optimizationleathers</li>
        <li>atk.devilstrandanimals</li>
        <li>seohyeon.optimizationmeats</li>
        <li>murmur.oocmovespeedboost</li>
        <li>taranchuk.performanceoptimizer</li>
        <li>owlchemist.toggleableoverlays</li>
        <li>lwm.deepstorage</li>
        <li>mehni.pickupandhaul</li>
        <li>dsw.plant24handsetableschedule</li>
        <li>uveren.plantanyinhydro</li>
        <li>premaritalsex.1trickponyta</li>
        <li>avilmask.psychicharmonizerlagfix</li>
        <li>mlie.questionableethicsenhanced</li>
        <li>ratys.rtsolarflareshield</li>
        <li>runnelatki.rabbieracemod</li>
        <li>sunny.rabbieenglishpatch</li>
        <li>goudaquiche.moharframework</li>
        <li>jkviolet.rakkleracemode</li>
        <li>rimworld.randomcoughdrop.geneassistant</li>
        <li>garwel.recruitslaves</li>
        <li>xrushha.reinstallablealtars</li>
        <li>yipnz.removeweatheroverlay</li>
        <li>mrkociak.droppodbaitscanner</li>
        <li>rusticfox.chickenplucker.w.io.rr_copy</li>
        <li>arandomkiwi.rimsaves</li>
        <li>sierra.rt.generaltraits</li>
        <li>sierra.rt.vanillatraitcolors</li>
        <li>mlie.roadsoftherim</li>
        <li>roolo.runandgun</li>
        <li>stormshark.samesexivf</li>
        <li>angryhornet.scenarioamender</li>
        <li>roolo.searchanddestroy</li>
        <li>sx99.biotech.genesup</li>
        <li>uuugggg.sharetheload</li>
        <li>vanillaexpanded.vaeaccessories</li>
        <li>vanillaexpanded.varme</li>
        <li>oskarpotocki.vfe.classical</li>
        <li>oskarpotocki.vanillafactionsexpanded.medievalmodule</li>
        <li>vanillaexpanded.vfeproduction</li>
        <li>vanillaexpanded.vwehw</li>
        <li>shavius.vepatches</li>
        <li>spacemoth.showknowntechprints</li>
        <li>kathanon.showweapontallies</li>
        <li>petetimessix.simplesidearms</li>
        <li>mlie.singleplanttexturepatch</li>
        <li>owlchemist.smartfarming</li>
        <li>uuugggg.smartmedicine</li>
        <li>sarg.smartspeed</li>
        <li>denev.smartturretcovering</li>
        <li>dhultgren.smarterconstruction</li>
        <li>legodude17.smartdecon</li>
        <li>weilbyte.snapout</li>
        <li>omgsplat.genesplit</li>
        <li>linkolas.stabilize</li>
        <li>thesepeople.thronesforall</li>
        <li>gt.sam.tilledsoil</li>
        <li>owlchemist.toggleablereadouts</li>
        <li>na.toxicresistantpowerarmour</li>
        <li>hobtook.tradeui</li>
        <li>superniquito.traiticons</li>
        <li>marvinkosh.ughyougotme</li>
        <li>mlie.ultratechshades</li>
        <li>malistaticy.underwhere</li>
        <li>owlchemist.undergroundpowerconduits</li>
        <li>madarauchiha.undraftaftertucking</li>
        <li>uuugggg.usebedrolls</li>
        <li>haplo.miscellaneous.training</li>
        <li>sirvan.misctrainingretexture</li>
        <li>vanillaexpanded.vaewaste</li>
        <li>vanillaexpanded.vappe</li>
        <li>vanillaexpanded.vanillabackstoriesexpanded</li>
        <li>vanillaexpanded.basegeneration</li>
        <li>neronix17.retexture.vanillabeards</li>
        <li>vanillaexpanded.vfepropsanddecor</li>
        <li>mlie.vanillabooksexpandedexpanded</li>
        <li>vanillaexpanded.vbrewe</li>
        <li>vanillaexpanded.vbrewecandt</li>
        <li>vanillaexpanded.vcookestews</li>
        <li>vanillaexpanded.vcookesushi</li>
        <li>vanillaexpanded.vee</li>
        <li>vanillaexpanded.vwec</li>
        <li>vanillaexpanded.vweq</li>
        <li>vanillaexpanded.vweft</li>
        <li>oskarpotocki.vanillaexpanded.ideologypatches</li>
        <li>oskarpotocki.vanillaexpanded.royaltypatches</li>
        <li>oskarpotocki.vfe.mechanoid</li>
        <li>vanillaexpanded.vcefaddon</li>
        <li>vanillaexpanded.vfearchitect</li>
        <li>vanillaexpanded.vfeart</li>
        <li>vanillaexpanded.vfefarming</li>
        <li>vanillaexpanded.vfemedical</li>
        <li>vanillaexpanded.vfesecurity</li>
        <li>vanillaexpanded.vfecore</li>
        <li>vanillaexpanded.vfespacer</li>
        <li>redmattis.vanillagenesrebalanced</li>
        <li>mrkociak.vegeneticsanimalworkimplantsaddons</li>
        <li>vanillaexpanded.vhe</li>
        <li>neronix17.retexture.vanillahair</li>
        <li>hourai.vanillahairsretex</li>
        <li>vanillaexpanded.helixiengas</li>
        <li>vanillaexpanded.vieat</li>
        <li>vanillaexpanded.ideo.dryads</li>
        <li>vanillaexpanded.viehar</li>
        <li>vanillaexpanded.ideo.iconsandsymbols</li>
        <li>vanillaexpanded.ideo.relicsandartifacts</li>
        <li>vanillaexpanded.viesas</li>
        <li>vanillaexpanded.vnutriente</li>
        <li>vanillaexpanded.outposts</li>
        <li>mlie.vanillaoutpostsexpandedexpandedranch</li>
        <li>mrhydralisk.voeadditionaloutposts</li>
        <li>mrhydralisk.voepowergrid</li>
        <li>vanillaexpanded.vpersonaweaponse</li>
        <li>vanillaexpanded.vplantse</li>
        <li>vanillaexpanded.vplantsemore</li>
        <li>vanillaexpanded.vplantsesucculents</li>
        <li>vanillaracesexpanded.customicons</li>
        <li>vanillaracesexpanded.genie</li>
        <li>vanillaracesexpanded.hussar</li>
        <li>vanillaracesexpanded.phytokin</li>
        <li>vanillaracesexpanded.sanguophage</li>
        <li>vanillaracesexpanded.saurid</li>
        <li>vanillaexpanded.vanillasocialinteractionsexpanded</li>
        <li>halituisamaricanous.vswbeam</li>
        <li>halituisamaricanous.vswbounce</li>
        <li>halituisamaricanous.vswebolt</li>
        <li>vse.diegoindustrial</li>
        <li>vse.empressevil</li>
        <li>vse.freyafierce</li>
        <li>vse.igorinvader</li>
        <li>vse.maynardmedieval</li>
        <li>vse.neronneolithic</li>
        <li>vse.oskarobnoxious</li>
        <li>vse.perrypersistent</li>
        <li>vanillaexpanded.vtexe</li>
        <li>vanillaexpanded.vtexvariations</li>
        <li>vanillaexpanded.vanillatradingexpanded</li>
        <li>vanillaexpanded.vweg</li>
        <li>vanillaexpanded.vwems</li>
        <li>vanillaexpanded.vwetb</li>
        <li>collalt.variouseyesgenes</li>
        <li>ogliss.toastehs.veinminer</li>
        <li>zzz.wallvitalsmonitor</li>
        <li>crustypeanut.wce2.core</li>
        <li>vanillaexpanded.vwenl</li>
        <li>brassrobo.vanillaexpandedunofficial.warcasketnonlethal</li>
        <li>metalocif.warcasketpersonaweapons</li>
        <li>mlie.wehadatrader</li>
        <li>mlie.weathercontroldevice</li>
        <li>co.uk.epicguru.whatsthatmod</li>
        <li>antisocialian.xenogeneregrowing2d</li>
        <li>papercrane1001.uvoee.trading</li>
        <li>vanillaexpanded.vanillatraitsexpanded</li>
        <li>dani.moretraits</li>
        <li>rh2.faction.void</li>
        <li>rh2.void.storyteller</li>
        <li>sr.modrimworld.factionalwar</li>
        <li>halabalooza.craftablearchotech</li>
        <li>pphhyy.sanguinaryanimals</li>
        <li>krkr.rocketman</li>
    </activeMods>
    <knownExpansions>
        <li>ludeon.rimworld</li>
        <li>ludeon.rimworld.royalty</li>
        <li>ludeon.rimworld.ideology</li>
        <li>ludeon.rimworld.biotech</li>
    </knownExpansions>
</ModsConfigData>
